<package>
  <description brief="iri_ry_oa_bridge">

     This is a node to interface a former local planner for the segway platform with the ROS world. 
     The former local planner is based on YARP in/out.
     WARNING : This node is too much tricky. Please, do not use it , unless deep knowledge about what is inside !

  </description>
  <author>andreu</author>
  <license>LGPL</license>
  <review status="unreviewed" notes=""/>
  <url>http://ros.org/wiki/iri_ry_oa_bridge</url>
  <depend package="roscpp"/>
  <depend package="iri_base_algorithm"/>
<!--   <depend package="iri_ry_oa_bridge"/> -->
  <depend package="geometry_msgs"/>
  <depend package="nav_msgs"/>
  <depend package="sensor_msgs"/>

</package>


